helloworld.py
ezesundayeze-0.1.dist-info/LICENCE
ezesundayeze-0.1.dist-info/METADATA
ezesundayeze-0.1.dist-info/WHEEL
ezesundayeze-0.1.dist-info/top_level.txt
ezesundayeze-0.1.dist-info/RECORD
