Metadata-Version: 2.1
Name: ezesundayeze
Version: 0.1
Summary: Say Hello
Home-page: UNKNOWN
License: UNKNOWN
Platform: UNKNOWN
Classifier: Programming Language :: Python :: 3
Classifier: Programming Language :: Python :: 3.5
Classifier: Programming Language :: Python :: 3.6
Classifier: Programming Language :: Python :: 3.7
Classifier: License :: OSI Approved :: Academic Free License (AFL) 
Classifier: Operating System :: OS Independent
